slh_sh/__init__.py
slh_sh/__main__.py
slh_sh/commands/__init__.py
slh_sh/commands/add.py
slh_sh/commands/extract.py
slh_sh/commands/get.py
slh_sh/commands/go.py
slh_sh/commands/query.py
slh_sh/commands/self.py
slh_sh/commands/sync.py
slh_sh/data/__init__.py
slh_sh/data/models.py
slh_sh/data/schemas.py
slh_sh/main.py
slh_sh/modules/__init__.py
slh_sh/modules/extract.py
slh_sh/modules/sync.py
slh_sh/utils/__init__.py
slh_sh/utils/config.py
slh_sh/utils/db.py
slh_sh/utils/file.py
slh_sh/utils/log.py
slh_sh/utils/pdf.py
slh_sh/utils/update.py
slh_sh-0.1.12.dist-info/METADATA
slh_sh-0.1.12.dist-info/WHEEL
slh_sh-0.1.12.dist-info/entry_points.txt
slh_sh-0.1.12.dist-info/RECORD
