Metadata-Version: 2.1
Name: slh-sh
Version: 0.1.12
Summary: 
Author: Nova Sky
Author-email: 2989791+0xnovasky@users.noreply.github.com
Requires-Python: >=3.10,<3.13
Classifier: Programming Language :: Python :: 3
Classifier: Programming Language :: Python :: 3.10
Classifier: Programming Language :: Python :: 3.11
Classifier: Programming Language :: Python :: 3.12
Requires-Dist: bs4 (>=0.0.1,<0.0.2)
Requires-Dist: gspread (>=5.11.2,<6.0.0)
Requires-Dist: oauth2client (>=4.1.3,<5.0.0)
Requires-Dist: pandas (>=2.1.1,<3.0.0)
Requires-Dist: pdfminer-six (>=20221105,<20221106)
Requires-Dist: pydantic (>=2.4.0,<3.0.0)
Requires-Dist: pymupdf (>=1.23.3,<2.0.0)
Requires-Dist: pyperclip (>=1.8.2,<2.0.0)
Requires-Dist: pyyaml (>=6.0.1,<7.0.0)
Requires-Dist: requests (>=2.31.0,<3.0.0)
Requires-Dist: scholarly (>=1.7.11,<2.0.0)
Requires-Dist: sqlalchemy (>=2.0.21,<3.0.0)
Requires-Dist: typer[all] (>=0.9.0,<0.10.0)
